animelistfetcher/__init__.py
animelistfetcher/animelist_fetcher.py
animelistfetcher-1.2.0.dist-info/licenses/LICENSE
animelistfetcher-1.2.0.dist-info/METADATA
animelistfetcher-1.2.0.dist-info/WHEEL
animelistfetcher-1.2.0.dist-info/top_level.txt
animelistfetcher-1.2.0.dist-info/RECORD
