Metadata-Version: 2.4
Name: animelistfetcher
Version: 1.2.0
Summary: A Python wrapper for my anime libraries
Author: Dominik Procházka
Maintainer: Dominik Procházka
Project-URL: Homepage, https://github.com/prochy-exe/animelistfetcher
Project-URL: Documentation, https://github.com/prochy-exe/animelistfetcher/wiki
Project-URL: Source, https://github.com/prochy-exe/animelistfetcher
Keywords: python,anilist,al,mal,myanimelist
Classifier: Development Status :: 5 - Production/Stable
Classifier: Framework :: Flask
Classifier: Topic :: Database
Classifier: Topic :: Games/Entertainment
Classifier: License :: OSI Approved :: GNU General Public License v3 or later (GPLv3+)
Classifier: Programming Language :: Python :: 3.8
Classifier: Programming Language :: Python :: 3.9
Classifier: Programming Language :: Python :: 3.10
Classifier: Programming Language :: Python :: 3.11
Classifier: Programming Language :: Python :: 3.12
Requires-Python: >=3.8
License-File: LICENSE
Requires-Dist: alfetcher
Requires-Dist: malfetcher
Dynamic: license-file
